pulumi_ovh/__init__.py
pulumi_ovh/_utilities.py
pulumi_ovh/cloud_project_containerregistry_iam.py
pulumi_ovh/cloud_project_database_valkey_user.py
pulumi_ovh/cloud_project_ssh_key.py
pulumi_ovh/domain_zone_dynhost_record.py
pulumi_ovh/get_cloud_project_database_valkey_user.py
pulumi_ovh/get_cloud_project_flavor.py
pulumi_ovh/get_cloud_project_gateway.py
pulumi_ovh/get_cloud_project_rancher_capabilities_plan.py
pulumi_ovh/get_cloud_project_rancher_capabilities_version.py
pulumi_ovh/get_cloud_project_ssh_key.py
pulumi_ovh/get_cloud_project_ssh_keys.py
pulumi_ovh/get_dbaas_logs_output_graylog_stream_url.py
pulumi_ovh/get_dedicated_server_orderable_bandwidth.py
pulumi_ovh/get_dedicated_server_orderable_bandwidth_vrack.py
pulumi_ovh/get_domain_zone_record.py
pulumi_ovh/get_domain_zone_records.py
pulumi_ovh/get_installation_template.py
pulumi_ovh/get_installation_templates.py
pulumi_ovh/get_location.py
pulumi_ovh/get_okms_secret.py
pulumi_ovh/get_ovhcloud_connect_config_pop_datacenter_extras.py
pulumi_ovh/get_ovhcloud_connect_config_pop_datacenters.py
pulumi_ovh/get_ovhcloud_connect_config_pops.py
pulumi_ovh/get_ovhcloud_connect_datacenters.py
pulumi_ovh/get_server.py
pulumi_ovh/get_servers.py
pulumi_ovh/get_storage_efs.py
pulumi_ovh/get_storage_efs_share_access_path.py
pulumi_ovh/get_storage_efs_share_access_paths.py
pulumi_ovh/get_vrack_networks.py
pulumi_ovh/iam_resource_tags.py
pulumi_ovh/outputs.py
pulumi_ovh/ovhcloud_connect_pop_config.py
pulumi_ovh/ovhcloud_connect_pop_datacenter_config.py
pulumi_ovh/ovhcloud_connect_pop_datacenter_extra_config.py
pulumi_ovh/provider.py
pulumi_ovh/pulumi-plugin.json
pulumi_ovh/py.typed
pulumi_ovh/storage_efs_share.py
pulumi_ovh/storage_efs_share_acl.py
pulumi_ovh/storage_efs_share_snapshot.py
pulumi_ovh/vrack_ipv6_routed_subrange.py
pulumi_ovh/cloud/__init__.py
pulumi_ovh/cloud/get_project.py
pulumi_ovh/cloud/get_projects.py
pulumi_ovh/cloud/outputs.py
pulumi_ovh/cloudproject/__init__.py
pulumi_ovh/cloudproject/_inputs.py
pulumi_ovh-2.9.0.dist-info/METADATA
pulumi_ovh-2.9.0.dist-info/WHEEL
pulumi_ovh-2.9.0.dist-info/top_level.txt
pulumi_ovh-2.9.0.dist-info/RECORD
